{
  "site": {
    "title": "Autonomous Content Creation Service",
    "description": "AI-powered content creation with unmatched quality and efficiency. Get professional content 24/7 without human intervention.",
    "url": "https://autonomous-content.com",
    "keywords": "AI content creation, autonomous writing, content marketing, SEO content, automated copywriting, AI writing service"
  },
  "services": [
    {
      "name": "Blog Posts & Articles",
      "description": "High-quality, SEO-optimized blog posts and articles that engage your audience and drive traffic",
      "pricing": "Starting at $50",
      "basePrice": 0.08
    },
    {
      "name": "Marketing Copy",
      "description": "Compelling marketing copy that converts visitors into customers across all channels",
      "pricing": "Starting at $75",
      "basePrice": 0.12
    },
    {
      "name": "Technical Documentation",
      "description": "Clear, comprehensive technical documentation that helps users understand complex systems",
      "pricing": "Starting at $100",
      "basePrice": 0.15
    },
    {
      "name": "Social Media Content",
      "description": "Engaging social media posts optimized for each platform to grow your audience",
      "pricing": "Starting at $25",
      "basePrice": 0.05
    },
    {
      "name": "Email Marketing",
      "description": "Persuasive email campaigns that drive opens, clicks, and conversions",
      "pricing": "Starting at $60",
      "basePrice": 0.10
    }
  ],
  "portfolio": [
    {
      "id": "ai-healthcare",
      "title": "AI in Healthcare: Revolutionary Changes",
      "category": "blog",
      "type": "Blog Post",
      "wordCount": 1200,
      "industry": "Technology",
      "excerpt": "Comprehensive analysis of AI's impact on healthcare delivery, featuring case studies and future predictions...",
      "metrics": {
        "engagement": "+300%",
        "seoScore": "95%"
      }
    },
    {
      "id": "saas-landing",
      "title": "SaaS Landing Page Copy",
      "category": "marketing",
      "type": "Marketing Copy",
      "wordCount": 800,
      "industry": "B2B SaaS",
      "excerpt": "Conversion-optimized landing page copy that increased sign-ups by 45% for a project management tool...",
      "metrics": {
        "conversions": "+45%",
        "tested": "A/B tested"
      }
    },
    {
      "id": "api-guide",
      "title": "API Integration Guide",
      "category": "technical",
      "type": "Technical Documentation",
      "wordCount": 2000,
      "industry": "Developer Tools",
      "excerpt": "Step-by-step API integration documentation with code examples and troubleshooting tips...",
      "metrics": {
        "helpedDevelopers": "500+",
        "completeness": "Comprehensive"
      }
    }
  ],
  "testimonials": [
    {
      "content": "The autonomous content system delivered exactly what we needed in record time. The quality exceeded our expectations and the SEO optimization was spot-on.",
      "author": "Sarah Chen",
      "company": "TechStart Inc.",
      "rating": 5
    },
    {
      "content": "We've been using the service for 6 months and it's revolutionized our content strategy. The consistency and speed are unmatched.",
      "author": "Michael Rodriguez",
      "company": "Growth Marketing Co.",
      "rating": 5
    },
    {
      "content": "As a startup, we needed high-quality content fast and affordable. This autonomous system gave us both without compromise.",
      "author": "Emma Thompson",
      "company": "InnovateLab",
      "rating": 5
    }
  ],
  "contact": {
    "email": "hello@autonomous-content.com",
    "phone": "+1 (555) 123-4567",
    "address": "123 AI Street, Tech City, TC 12345"
  },
  "stats": {
    "contentPieces": "1000+",
    "clientSatisfaction": "95%",
    "averageDelivery": "24hrs",
    "roiImprovement": "300%"
  },
  "seo": {
    "metaTitle": "Autonomous Content Creation Service - AI-Powered Writing 24/7",
    "metaDescription": "Get professional content created by AI around the clock. Blog posts, marketing copy, technical docs - all optimized for SEO and conversions.",
    "focusKeywords": [
      "autonomous content creation",
      "AI writing service",
      "automated copywriting",
      "24/7 content generation",
      "SEO content writing"
    ]
  },
  "features": [
    {
      "icon": "🚀",
      "title": "Lightning Fast",
      "description": "Content delivered in hours, not days"
    },
    {
      "icon": "🎯",
      "title": "SEO Optimized",
      "description": "Built-in SEO best practices for better rankings"
    },
    {
      "icon": "🔄",
      "title": "Always Available",
      "description": "24/7/365 autonomous operation"
    },
    {
      "icon": "💎",
      "title": "Premium Quality",
      "description": "Multi-pass AI review ensures excellence"
    },
    {
      "icon": "📈",
      "title": "Data-Driven",
      "description": "Optimized based on performance analytics"
    },
    {
      "icon": "💰",
      "title": "Cost-Effective",
      "description": "Premium quality at competitive prices"
    }
  ],
  "pages": {
    "home": {
      "title": "Home",
      "description": "Professional autonomous content creation service powered by AI"
    },
    "services": {
      "title": "Services", 
      "description": "Comprehensive content creation services including blog posts, social media, and more"
    },
    "portfolio": {
      "title": "Portfolio",
      "description": "Examples of high-quality content created by our autonomous system"
    },
    "about": {
      "title": "About",
      "description": "Learn about our autonomous content creation technology and approach"
    },
    "contact": {
      "title": "Contact",
      "description": "Get in touch to start your autonomous content creation project"
    },
    "onboarding": {
      "title": "Get Started",
      "description": "Set up your personalized content strategy in just 15 minutes"
    }
  }
}